urban_footprinter/__init__.py
urban_footprinter/settings.py
urban_footprinter-0.3.1.dist-info/licenses/LICENSE
urban_footprinter-0.3.1.dist-info/METADATA
urban_footprinter-0.3.1.dist-info/WHEEL
urban_footprinter-0.3.1.dist-info/top_level.txt
urban_footprinter-0.3.1.dist-info/RECORD
