Metadata-Version: 2.4
Name: urban-footprinter
Version: 0.3.1
Summary: A convolution-based approach to detect urban extents.
Author-email: Martí Bosch <marti.bosch@epfl.ch>
License-Expression: GPL-3.0-or-later
Project-URL: Repository, https://github.com/martibosch/urban-footprinter
Classifier: Natural Language :: English
Classifier: Programming Language :: Python :: 3
Classifier: Programming Language :: Python :: 3.10
Classifier: Programming Language :: Python :: 3.11
Classifier: Programming Language :: Python :: 3.12
Classifier: Programming Language :: Python :: 3.13
Requires-Python: >=3.10
License-File: LICENSE
Requires-Dist: numpy>=1.15
Requires-Dist: opencv-python>=4.0.0
Requires-Dist: pandas>=0.19.0
Requires-Dist: rasterio>=1.0.0
Requires-Dist: scipy>=1.0.0
Requires-Dist: shapely>=1.0.0
Provides-Extra: test
Requires-Dist: black; extra == "test"
Requires-Dist: coverage[toml]; extra == "test"
Requires-Dist: pytest; extra == "test"
Requires-Dist: pytest-cov; extra == "test"
Requires-Dist: python-dotenv; extra == "test"
Requires-Dist: ruff; extra == "test"
Provides-Extra: dev
Requires-Dist: build; extra == "dev"
Requires-Dist: commitizen; extra == "dev"
Requires-Dist: pre-commit; extra == "dev"
Requires-Dist: pip; extra == "dev"
Requires-Dist: toml; extra == "dev"
Requires-Dist: tox; extra == "dev"
Requires-Dist: twine; extra == "dev"
Provides-Extra: doc
Requires-Dist: myst-parser; extra == "doc"
Requires-Dist: sphinx; extra == "doc"
Dynamic: license-file
